odoo/addons/stock_route_mto/README.rst
odoo/addons/stock_route_mto/__init__.py
odoo/addons/stock_route_mto/__manifest__.py
odoo/addons/stock_route_mto/data/stock_route.xml
odoo/addons/stock_route_mto/i18n/it.po
odoo/addons/stock_route_mto/i18n/stock_route_mto.pot
odoo/addons/stock_route_mto/models/__init__.py
odoo/addons/stock_route_mto/models/stock_route.py
odoo/addons/stock_route_mto/readme/CONTRIBUTORS.rst
odoo/addons/stock_route_mto/readme/DESCRIPTION.rst
odoo/addons/stock_route_mto/readme/USAGE.rst
odoo/addons/stock_route_mto/static/description/icon.png
odoo/addons/stock_route_mto/static/description/index.html
odoo/addons/stock_route_mto/views/stock_route.xml
odoo14_addon_stock_route_mto-14.0.1.0.1.dev3.dist-info/METADATA
odoo14_addon_stock_route_mto-14.0.1.0.1.dev3.dist-info/WHEEL
odoo14_addon_stock_route_mto-14.0.1.0.1.dev3.dist-info/top_level.txt
odoo14_addon_stock_route_mto-14.0.1.0.1.dev3.dist-info/RECORD
